thesmuggler.py
thesmuggler-1.0.1.dist-info/DESCRIPTION.rst
thesmuggler-1.0.1.dist-info/METADATA
thesmuggler-1.0.1.dist-info/RECORD
thesmuggler-1.0.1.dist-info/WHEEL
thesmuggler-1.0.1.dist-info/metadata.json
thesmuggler-1.0.1.dist-info/top_level.txt
