Metadata-Version: 1.1
Name: thesmuggler
Version: 1.0.1
Summary: Sidestep import and load Python files as relative paths
Home-page: https://github.com/fny/thesmuggler
Author: Faraz Yashar
Author-email: faraz.yashar@gmail.com
License: MIT
Keywords: import modules packages files
Platform: UNKNOWN
Classifier: Development Status :: 5 - Production/Stable
Classifier: Intended Audience :: Developers
Classifier: Topic :: Software Development
Classifier: Topic :: Utilities
Classifier: License :: OSI Approved :: MIT License
Classifier: Programming Language :: Python :: 2.7
Classifier: Programming Language :: Python :: 3
